idl2js/__init__.py
idl2js/__main__.py
idl2js/dependency_graph.py
idl2js/environment.py
idl2js/exceptions.py
idl2js/idl_processor.py
idl2js/idl_to_intermediate.py
idl2js/intermediate/__init__.py
idl2js/intermediate/ftypes.py
idl2js/intermediate_to_js.py
idl2js/js/__init__.py
idl2js/js/built_in/__init__.py
idl2js/js/built_in/constants.py
idl2js/js/built_in/jtypes.py
idl2js/js/built_in/media_types.py
idl2js/js/built_in/mime/application.csv
idl2js/js/built_in/mime/audio.csv
idl2js/js/built_in/mime/font.csv
idl2js/js/built_in/mime/image.csv
idl2js/js/built_in/mime/message.csv
idl2js/js/built_in/mime/model.csv
idl2js/js/built_in/mime/multipart.csv
idl2js/js/built_in/mime/text.csv
idl2js/js/built_in/mime/video.csv
idl2js/js/const.py
idl2js/js/instance.py
idl2js/js/mutator.py
idl2js/js/nodes.py
idl2js/js/statements.py
idl2js/js/unparser.py
idl2js/js/utils.py
idl2js/js/variable.py
idl2js/logger.py
idl2js/main.py
idl2js/std/__init__.py
idl2js/std/builder.py
idl2js/std/integer.py
idl2js/std/string.py
idl2js/std/typed_array.py
idl2js/targets.py
idl2js/transpiler.py
idl2js/utils.py
idl2js/visitor.py
idl2js/webidl/__init__.py
idl2js/webidl/generated/WebIDLLexer.interp
idl2js/webidl/generated/WebIDLLexer.py
idl2js/webidl/generated/WebIDLLexer.tokens
idl2js/webidl/generated/WebIDLParser.interp
idl2js/webidl/generated/WebIDLParser.py
idl2js/webidl/generated/WebIDLParser.tokens
idl2js/webidl/generated/WebIDLParserVisitor.py
idl2js/webidl/generated/__init__.py
idl2js/webidl/idls/common.webidl
idl2js/webidl/nodes.py
idl2js/webidl/parser.py
idl2js/webidl/utils.py
idl2js/webidl/visitor.py
idl2js/webidl/webidl.py
idl2js-0.1.3.dist-info/LICENSE
idl2js-0.1.3.dist-info/WHEEL
idl2js-0.1.3.dist-info/METADATA
idl2js-0.1.3.dist-info/RECORD
