Metadata-Version: 2.1
Name: idl2js
Version: 0.1.3
Summary: Grammar-based Fuzzer that uses WebIDL as a grammar.
Home-page: https://github.com/PrVrSs/idl2js
License: Apache-2.0
Keywords: WebIDL,fuzzer,ast,grammar,fuzzing,transpiler
Author: Sergey Reshetnikov
Author-email: resh.sersh@gmail.com
Requires-Python: >=3.10,<4.0
Classifier: License :: OSI Approved :: Apache Software License
Classifier: Programming Language :: Python :: 3
Classifier: Programming Language :: Python :: 3.10
Requires-Dist: antlr4-python3-runtime (==4.10)
Requires-Dist: attrs (>=21.4.0,<22.0.0)
Requires-Dist: click (>=8.0.4,<9.0.0)
Requires-Dist: graphviz (>=0.19.1,<0.20.0)
Requires-Dist: more-itertools (>=8.12.0,<9.0.0)
Requires-Dist: stringcase (>=1.2.0,<2.0.0)
Project-URL: Repository, https://github.com/PrVrSs/idl2js
